bdtool.py
bdtool-1.2.5.dist-info/METADATA
bdtool-1.2.5.dist-info/WHEEL
bdtool-1.2.5.dist-info/entry_points.txt
bdtool-1.2.5.dist-info/top_level.txt
bdtool-1.2.5.dist-info/RECORD
